can_sontheim/SIECA132.pdf
can_sontheim/__init__.py
can_sontheim/_canlib.py
can_sontheim/constants.py
can_sontheim/devices.py
can_sontheim/interprocess communication.url
can_sontheim/structures.py
can_sontheim/version.py
python_can_sontheim-0.1.3.dist-info/LICENSE.txt
python_can_sontheim-0.1.3.dist-info/METADATA
python_can_sontheim-0.1.3.dist-info/WHEEL
python_can_sontheim-0.1.3.dist-info/entry_points.txt
python_can_sontheim-0.1.3.dist-info/top_level.txt
python_can_sontheim-0.1.3.dist-info/RECORD
