Metadata-Version: 2.1
Name: python-can-sontheim
Version: 0.1.3
Summary: A python-can interface driver for Sontheim Industrie Elektronik CAN bus interfaces
Author-email: Matt Woodhead <woody.w62@gmail.com>
License: GNU Lesser General Public License v3 (LGPLv3)
Project-URL: homepage, https://github.com/MattWoodhead/python-can-sontheim
Project-URL: documentation, https://github.com/MattWoodhead/python-can-sontheim
Project-URL: repository, https://github.com/MattWoodhead/python-can-sontheim
Keywords: CANbus,Sontheim,python-can,CANfox
Classifier: Development Status :: 3 - Alpha
Classifier: License :: OSI Approved :: GNU Lesser General Public License v3 (LGPLv3)
Classifier: Operating System :: Microsoft :: Windows
Classifier: Programming Language :: Python :: 3
Classifier: Intended Audience :: Developers
Classifier: Intended Audience :: End Users/Desktop
Classifier: Intended Audience :: Manufacturing
Classifier: Environment :: Plugins
Requires-Python: >=3.7
License-File: LICENSE.txt
Requires-Dist: python-can
Provides-Extra: dev
Requires-Dist: windows-curses ; extra == 'dev'
Requires-Dist: parameterized ; extra == 'dev'
Requires-Dist: pytest ; extra == 'dev'
